beat_craft_sdk/__init__.py
beat_craft_sdk/config.py
beat_craft_sdk/core.py
beat_craft_sdk/craft_strategy.py
beat_craft_sdk/crafting_with_backingtrack.py
beat_craft_sdk/crafting_with_genetic.py
beat_craft_sdk/transformer.py
beatCraftSdk-0.0.1.dist-info/METADATA
beatCraftSdk-0.0.1.dist-info/WHEEL
beatCraftSdk-0.0.1.dist-info/top_level.txt
beatCraftSdk-0.0.1.dist-info/RECORD
